yape/__init__.py
yape/__main__.py
yape/climodule.py
yape/gn.py
yape/grun.py
yape/mingraphmod.py
yape/nodeop.py
yape/nodestate.py
yape/pathprovider.py
yape/py.typed
yape/resmod.py
yape/ty.py
yape/util.py
yape/walkproto.py
yape/yapecontext.py
yape-0.3.0.dist-info/LICENSE.txt
yape-0.3.0.dist-info/METADATA
yape-0.3.0.dist-info/WHEEL
yape-0.3.0.dist-info/entry_points.txt
yape-0.3.0.dist-info/top_level.txt
yape-0.3.0.dist-info/RECORD
