Metadata-Version: 2.1
Name: yape
Version: 0.3.0
Summary: Yape - Yet another pipeline executor
Home-page: https://github.com/guludo/yape
Keywords: pipeline
Classifier: Development Status :: 3 - Alpha
Classifier: Intended Audience :: Developers
Classifier: License :: OSI Approved :: Mozilla Public License 2.0 (MPL 2.0)
Classifier: Programming Language :: Python :: 3
License-File: LICENSE.txt
Requires-Dist: argparse-subdec (<1.0,>=0.2.1)
Requires-Dist: dill (~=0.3.4)
Provides-Extra: dev
Requires-Dist: mypy (<1.0,>=0.910) ; extra == 'dev'
Requires-Dist: pytest (~=7.1.3) ; extra == 'dev'
